rustsgxgen/__init__.py
rustsgxgen/conf.py
rustsgxgen/generator.py
rustsgxgen/initialization.py
rustsgxgen/runner.py
rustsgxgen/utils.py
rustsgxgen/stubs/README.md
rustsgxgen/stubs/__authentic_execution.rs
rustsgxgen/stubs/common_deps.toml
rustsgxgen/stubs/constants.rs
rustsgxgen/stubs/main.rs
rustsgxgen/stubs/mods_uses.rs
rustsgxgen/stubs/output.rs
rustsgxgen/stubs/request.rs
rustsgxgen/stubs/runner_native/__run.rs
rustsgxgen/stubs/runner_native/dependencies.toml
rustsgxgen/stubs/runner_sgx/__run.rs
rustsgxgen/stubs/runner_sgx/dependencies.toml
rust_sgx_gen-0.3.8.dist-info/LICENSE
rust_sgx_gen-0.3.8.dist-info/METADATA
rust_sgx_gen-0.3.8.dist-info/WHEEL
rust_sgx_gen-0.3.8.dist-info/entry_points.txt
rust_sgx_gen-0.3.8.dist-info/top_level.txt
rust_sgx_gen-0.3.8.dist-info/RECORD
