Metadata-Version: 2.1
Name: rust-sgx-gen
Version: 0.3.8
Summary: Rust code generator for the Authentic Execution framework
Home-page: https://github.com/AuthenticExecution/rust-sgx-gen
Author: Gianluca Scopelliti
Author-email: gianlu.1033@gmail.com
License: UNKNOWN
Platform: UNKNOWN
Classifier: Programming Language :: Python :: 3
Classifier: License :: OSI Approved :: MIT License
Classifier: Operating System :: POSIX :: Linux
Requires-Python: >=3.6
Requires-Dist: toml (==0.10.2)
Requires-Dist: colorlog (==4.6.2)
